{"Authors":" Teresa Lebel, Anna E Syme","Year":" 2011","Title":" Sequestrate Agaricus and Macrolepiota from Australia: new\nspecies and combinations and their position in a calibrated\nphylogeny","Journal":" Mycologia","Volume":"","Issue":"","Pages":"","Keywords":" Agaricaceae, Endoptychum, nomenclature, taxonomy, timing\nof evolution","DOI":"","Abstract":"","trees":[{"tree_label":"Chlorophyllum","ntax":"87","rootedtree":"TRUE","title":"Sequestrate Agaricus and Macrolepiota from\nAustralia","tree_kind":"Species Tree","tree_type":"Consensus","tree_quality":"Unrated","phylotree_id":"tree_50209.phy"},{"tree_label":"ITS calibrated","ntax":"87","rootedtree":"TRUE","title":"Sequestrate Agaricus and Macrolepiota from\nAustralia","tree_kind":"Species Tree","tree_type":"Consensus","tree_quality":"Unrated","phylotree_id":"tree_50211.phy"},{"tree_label":"Agaricus","ntax":"102","rootedtree":"TRUE","title":"Sequestrate Agaricus and Macrolepiota from\nAustralia","tree_kind":"Species Tree","tree_type":"Consensus","tree_quality":"Unrated","phylotree_id":"tree_50208.phy"},{"tree_label":"LSU","ntax":"72","rootedtree":"TRUE","title":"Sequestrate Agaricus and Macrolepiota from\nAustralia","tree_kind":"Species Tree","tree_type":"Consensus","tree_quality":"Unrated","phylotree_id":"tree_50207.phy"}]}