{"Authors":" Maria Paz Catanzaro, Marisa Graciela Bonasora, Pablo Rafael\nSperanza, Marcelo Medina-Nicolas, José F. M. Valls, Gabriel Hugo\nRua","Year":" 2015","Title":" Paspalum chilense (Poaceae, Paspaleae): A new species from\nsouthern South America.","Journal":" Phytotaxa","Volume":" 197","Issue":" 4","Pages":" 245-256","Keywords":" Notata group, Paspalum chilense, South America.","DOI":" 10.11646/phytotaxa.197.4.2","Abstract":" Paspalum chilense, a new species from Chile belonging to\nthe informal Notata group, is described and illustrated on the basis of\nmorphological, cytological and molecular evidence. Our evidence supports\nits affinity with P. barretoi and P. nummularium, from Brazil, from\nwhich it has been probably diverged by vicariant speciation. The limited\navailable material of the new species was previously identified as P.\npumilum or P. minus. A new key to the species of the core Notata group\nis provided.","trees":[{"tree_label":"tnt 1","ntax":"9","rootedtree":"TRUE","title":"Tr87169","tree_kind":"NA","tree_type":"NA","tree_quality":"NA","phylotree_id":"tree_87169.phy"}]}