{"Authors":" Ulla Kaasalainen, Veera Tuovinen, Kaisa Jauhiainen,\nGeoffrey Mwachala, Petri Pellikka, Jouko Rikkinen","Year":" 2017","Title":" Photobiont-mediated cyanolichen guilds in a tropical\nbiodiversity hotspot","Journal":"","Volume":"","Issue":"","Pages":"","Keywords":"","DOI":"","Abstract":"","trees":[{"tree_label":"con 50 majrule","ntax":"107","rootedtree":"TRUE","title":"Tr104244","tree_kind":"NA","tree_type":"NA","tree_quality":"NA","phylotree_id":"tree_104244.phy"},{"tree_label":"con 50 majrule","ntax":"107","rootedtree":"TRUE","title":"Tr104245","tree_kind":"NA","tree_type":"NA","tree_quality":"NA","phylotree_id":"tree_104245.phy"},{"tree_label":"con 50 majrule","ntax":"32","rootedtree":"TRUE","title":"Tr104246","tree_kind":"NA","tree_type":"NA","tree_quality":"NA","phylotree_id":"tree_104246.phy"},{"tree_label":"con 50 majrule","ntax":"32","rootedtree":"TRUE","title":"Tr104247","tree_kind":"NA","tree_type":"NA","tree_quality":"NA","phylotree_id":"tree_104247.phy"}]}