{"Authors":" Zhang Ying","Year":" 2017","Title":" Genera of phytopathogenic fungi: GOPHY 1","Journal":" STUDIES IN MYCOLOGY","Volume":"","Issue":"","Pages":"","Keywords":" DNA barcodes, Fungal systematics, Phytopathogenic fungi,\nPlant pathology, Taxonomy, Typifications.","DOI":"","Abstract":" Genera of Phytopathogenic Fungi (GOPHY) is introduced as a\nnew series of publications in order to provide a stable platform for the\ntaxonomy of phytopathogenic fungi. This first paper focuses on 21 genera\nof phytopathogenic fungi: Bipolaris, Boeremia, Calonectria,\nCeratocystis, Cladosporium, Colletotrichum, Coniella, Curvularia,\nMonilinia, Neofabraea, Neofusicoccum, Pilidium, Pleiochaeta, Plenodomus,\nProtostegia, Pseudopyricularia, Puccinia, Saccharata, Thyrostroma,\nVenturia and Wilsonomyces. For each genus, a morphological description\nand information about its pathology, distribution, hosts and disease\nsymptoms are provided. In addition, this information is linked to\nprimary and secondary DNA barcodes of the presently accepted species,\nand relevant literature. Moreover, several novelties are introduced,\ni.e. new genera, species and combinations, and neo-, lecto- and epitypes\ndesignated to provide a stable taxonomy. This first paper includes one\nnew genus, 26 new species, nine new combinations, and four typifications\nof older names.","trees":[{"tree_label":"Strict","ntax":"1","rootedtree":"TRUE","title":"Tr104973","tree_kind":"NA","tree_type":"NA","tree_quality":"NA","phylotree_id":"tree_104973.phy"},{"tree_label":"PAUP 1","ntax":"37","rootedtree":"TRUE","title":"Tr104972","tree_kind":"NA","tree_type":"NA","tree_quality":"NA","phylotree_id":"tree_104972.phy"},{"tree_label":"con 50 majrule","ntax":"1","rootedtree":"TRUE","title":"Tr105004","tree_kind":"NA","tree_type":"NA","tree_quality":"NA","phylotree_id":"tree_105004.phy"},{"tree_label":"PAUP 1","ntax":"37","rootedtree":"TRUE","title":"Tr104974","tree_kind":"NA","tree_type":"NA","tree_quality":"NA","phylotree_id":"tree_104974.phy"},{"tree_label":"PAUP 2","ntax":"37","rootedtree":"TRUE","title":"Tr104975","tree_kind":"NA","tree_type":"NA","tree_quality":"NA","phylotree_id":"tree_104975.phy"},{"tree_label":"PAUP 3","ntax":"37","rootedtree":"TRUE","title":"Tr104976","tree_kind":"NA","tree_type":"NA","tree_quality":"NA","phylotree_id":"tree_104976.phy"},{"tree_label":"PAUP 4","ntax":"37","rootedtree":"TRUE","title":"Tr104977","tree_kind":"NA","tree_type":"NA","tree_quality":"NA","phylotree_id":"tree_104977.phy"},{"tree_label":"PAUP 5","ntax":"37","rootedtree":"TRUE","title":"Tr104978","tree_kind":"NA","tree_type":"NA","tree_quality":"NA","phylotree_id":"tree_104978.phy"},{"tree_label":"PAUP 6","ntax":"37","rootedtree":"TRUE","title":"Tr104979","tree_kind":"NA","tree_type":"NA","tree_quality":"NA","phylotree_id":"tree_104979.phy"},{"tree_label":"PAUP 7","ntax":"37","rootedtree":"TRUE","title":"Tr104980","tree_kind":"NA","tree_type":"NA","tree_quality":"NA","phylotree_id":"tree_104980.phy"},{"tree_label":"PAUP 8","ntax":"37","rootedtree":"TRUE","title":"Tr104981","tree_kind":"NA","tree_type":"NA","tree_quality":"NA","phylotree_id":"tree_104981.phy"},{"tree_label":"PAUP 9","ntax":"37","rootedtree":"TRUE","title":"Tr104982","tree_kind":"NA","tree_type":"NA","tree_quality":"NA","phylotree_id":"tree_104982.phy"},{"tree_label":"PAUP 10","ntax":"37","rootedtree":"TRUE","title":"Tr104983","tree_kind":"NA","tree_type":"NA","tree_quality":"NA","phylotree_id":"tree_104983.phy"},{"tree_label":"PAUP 11","ntax":"37","rootedtree":"TRUE","title":"Tr104984","tree_kind":"NA","tree_type":"NA","tree_quality":"NA","phylotree_id":"tree_104984.phy"},{"tree_label":"PAUP 12","ntax":"37","rootedtree":"TRUE","title":"Tr104985","tree_kind":"NA","tree_type":"NA","tree_quality":"NA","phylotree_id":"tree_104985.phy"},{"tree_label":"PAUP 13","ntax":"37","rootedtree":"TRUE","title":"Tr104986","tree_kind":"NA","tree_type":"NA","tree_quality":"NA","phylotree_id":"tree_104986.phy"},{"tree_label":"PAUP 14","ntax":"37","rootedtree":"TRUE","title":"Tr104987","tree_kind":"NA","tree_type":"NA","tree_quality":"NA","phylotree_id":"tree_104987.phy"},{"tree_label":"PAUP 15","ntax":"37","rootedtree":"TRUE","title":"Tr104988","tree_kind":"NA","tree_type":"NA","tree_quality":"NA","phylotree_id":"tree_104988.phy"},{"tree_label":"PAUP 16","ntax":"37","rootedtree":"TRUE","title":"Tr104989","tree_kind":"NA","tree_type":"NA","tree_quality":"NA","phylotree_id":"tree_104989.phy"},{"tree_label":"PAUP 17","ntax":"37","rootedtree":"TRUE","title":"Tr104990","tree_kind":"NA","tree_type":"NA","tree_quality":"NA","phylotree_id":"tree_104990.phy"},{"tree_label":"PAUP 18","ntax":"37","rootedtree":"TRUE","title":"Tr104991","tree_kind":"NA","tree_type":"NA","tree_quality":"NA","phylotree_id":"tree_104991.phy"},{"tree_label":"PAUP 19","ntax":"37","rootedtree":"TRUE","title":"Tr104992","tree_kind":"NA","tree_type":"NA","tree_quality":"NA","phylotree_id":"tree_104992.phy"},{"tree_label":"PAUP 20","ntax":"37","rootedtree":"TRUE","title":"Tr104993","tree_kind":"NA","tree_type":"NA","tree_quality":"NA","phylotree_id":"tree_104993.phy"},{"tree_label":"PAUP 21","ntax":"37","rootedtree":"TRUE","title":"Tr104994","tree_kind":"NA","tree_type":"NA","tree_quality":"NA","phylotree_id":"tree_104994.phy"},{"tree_label":"PAUP 22","ntax":"37","rootedtree":"TRUE","title":"Tr104995","tree_kind":"NA","tree_type":"NA","tree_quality":"NA","phylotree_id":"tree_104995.phy"},{"tree_label":"PAUP 23","ntax":"37","rootedtree":"TRUE","title":"Tr104996","tree_kind":"NA","tree_type":"NA","tree_quality":"NA","phylotree_id":"tree_104996.phy"},{"tree_label":"PAUP 24","ntax":"37","rootedtree":"TRUE","title":"Tr104997","tree_kind":"NA","tree_type":"NA","tree_quality":"NA","phylotree_id":"tree_104997.phy"},{"tree_label":"PAUP 25","ntax":"37","rootedtree":"TRUE","title":"Tr104998","tree_kind":"NA","tree_type":"NA","tree_quality":"NA","phylotree_id":"tree_104998.phy"},{"tree_label":"PAUP 26","ntax":"37","rootedtree":"TRUE","title":"Tr104999","tree_kind":"NA","tree_type":"NA","tree_quality":"NA","phylotree_id":"tree_104999.phy"},{"tree_label":"PAUP 27","ntax":"37","rootedtree":"TRUE","title":"Tr105000","tree_kind":"NA","tree_type":"NA","tree_quality":"NA","phylotree_id":"tree_105000.phy"},{"tree_label":"PAUP 28","ntax":"37","rootedtree":"TRUE","title":"Tr105001","tree_kind":"NA","tree_type":"NA","tree_quality":"NA","phylotree_id":"tree_105001.phy"},{"tree_label":"PAUP 29","ntax":"37","rootedtree":"TRUE","title":"Tr105002","tree_kind":"NA","tree_type":"NA","tree_quality":"NA","phylotree_id":"tree_105002.phy"},{"tree_label":"PAUP 172","ntax":"37","rootedtree":"TRUE","title":"Tr105003","tree_kind":"NA","tree_type":"NA","tree_quality":"NA","phylotree_id":"tree_105003.phy"},{"tree_label":"con 50 majrule","ntax":"1","rootedtree":"TRUE","title":"Tr105005","tree_kind":"NA","tree_type":"NA","tree_quality":"NA","phylotree_id":"tree_105005.phy"}]}