{"Authors":" NA","Year":" NA","Title":" NA","Journal":" NA","Volume":" NA","Issue":" NA","Pages":" NA","Keywords":" NA","DOI":" NA","Abstract":" NA","trees":[{"tree_label":"con 50 majrule","ntax":"711","rootedtree":"TRUE","title":"Tr124445","tree_kind":"NA","tree_type":"NA","tree_quality":"NA","phylotree_id":"tree_124445.phy"},{"tree_label":"con 50 majrule","ntax":"712","rootedtree":"TRUE","title":"Tr124446","tree_kind":"NA","tree_type":"NA","tree_quality":"NA","phylotree_id":"tree_124446.phy"},{"tree_label":"con 50 majrule","ntax":"712","rootedtree":"TRUE","title":"Tr124337","tree_kind":"NA","tree_type":"NA","tree_quality":"NA","phylotree_id":"tree_124337.phy"}]}