{"Authors":" James Theodore Melton, Juan Lopez-Bautista","Year":" 2020","Title":" DIVERSITY OF THE MACROALGAL GENUS ULVA (ULVOPHYCEAE,\nCHLOROPHYTA) FROM THE EAST AND GULF COAST OF THE UNITED STATES BASED ON\nMOLECULAR DATA","Journal":" Journal of Phycology","Volume":"","Issue":"","Pages":"","Keywords":"","DOI":"","Abstract":"","trees":[{"tree_label":"TREE1","ntax":"120","rootedtree":"TRUE","title":"Tr125383","tree_kind":"NA","tree_type":"NA","tree_quality":"NA","phylotree_id":"tree_125383.phy"},{"tree_label":"TREE1","ntax":"92","rootedtree":"TRUE","title":"Tr125381","tree_kind":"NA","tree_type":"NA","tree_quality":"NA","phylotree_id":"tree_125381.phy"},{"tree_label":"TREE1","ntax":"83","rootedtree":"TRUE","title":"Tr125382","tree_kind":"NA","tree_type":"NA","tree_quality":"NA","phylotree_id":"tree_125382.phy"}]}