{"Authors":" NA","Year":" NA","Title":" NA","Journal":" NA","Volume":" NA","Issue":" NA","Pages":" NA","Keywords":" NA","DOI":" NA","Abstract":" NA","trees":[{"tree_label":"Imported tree 1","ntax":"18","rootedtree":"TRUE","title":"Tr125921","tree_kind":"NA","tree_type":"NA","tree_quality":"NA","phylotree_id":"tree_125921.phy"},{"tree_label":"Imported tree 1","ntax":"19","rootedtree":"TRUE","title":"Tr125923","tree_kind":"NA","tree_type":"NA","tree_quality":"NA","phylotree_id":"tree_125923.phy"},{"tree_label":"Imported tree 1","ntax":"19","rootedtree":"TRUE","title":"Tr125924","tree_kind":"NA","tree_type":"NA","tree_quality":"NA","phylotree_id":"tree_125924.phy"},{"tree_label":"Imported tree 1","ntax":"20","rootedtree":"TRUE","title":"Tr125925","tree_kind":"NA","tree_type":"NA","tree_quality":"NA","phylotree_id":"tree_125925.phy"},{"tree_label":"Imported tree 1","ntax":"21","rootedtree":"TRUE","title":"Tr125926","tree_kind":"NA","tree_type":"NA","tree_quality":"NA","phylotree_id":"tree_125926.phy"},{"tree_label":"con 50 majrule","ntax":"19","rootedtree":"TRUE","title":"Tr125916","tree_kind":"NA","tree_type":"NA","tree_quality":"NA","phylotree_id":"tree_125916.phy"},{"tree_label":"Imported tree 1","ntax":"18","rootedtree":"TRUE","title":"Tr125913","tree_kind":"NA","tree_type":"NA","tree_quality":"NA","phylotree_id":"tree_125913.phy"},{"tree_label":"Imported tree 1","ntax":"15","rootedtree":"TRUE","title":"Tr125912","tree_kind":"NA","tree_type":"NA","tree_quality":"NA","phylotree_id":"tree_125912.phy"},{"tree_label":"Imported tree 1","ntax":"19","rootedtree":"TRUE","title":"Tr125917","tree_kind":"NA","tree_type":"NA","tree_quality":"NA","phylotree_id":"tree_125917.phy"},{"tree_label":"Imported tree 1","ntax":"15","rootedtree":"TRUE","title":"Tr125911","tree_kind":"NA","tree_type":"NA","tree_quality":"NA","phylotree_id":"tree_125911.phy"},{"tree_label":"Imported tree 1","ntax":"22","rootedtree":"TRUE","title":"Tr125914","tree_kind":"NA","tree_type":"NA","tree_quality":"NA","phylotree_id":"tree_125914.phy"},{"tree_label":"Imported tree 1","ntax":"25","rootedtree":"TRUE","title":"Tr125915","tree_kind":"NA","tree_type":"NA","tree_quality":"NA","phylotree_id":"tree_125915.phy"},{"tree_label":"Imported tree 1","ntax":"18","rootedtree":"TRUE","title":"Tr125918","tree_kind":"NA","tree_type":"NA","tree_quality":"NA","phylotree_id":"tree_125918.phy"},{"tree_label":"Imported tree 1","ntax":"25","rootedtree":"TRUE","title":"Tr125919","tree_kind":"NA","tree_type":"NA","tree_quality":"NA","phylotree_id":"tree_125919.phy"},{"tree_label":"Imported tree 1","ntax":"19","rootedtree":"TRUE","title":"Tr125920","tree_kind":"NA","tree_type":"NA","tree_quality":"NA","phylotree_id":"tree_125920.phy"},{"tree_label":"Imported tree 1","ntax":"22","rootedtree":"TRUE","title":"Tr125922","tree_kind":"NA","tree_type":"NA","tree_quality":"NA","phylotree_id":"tree_125922.phy"},{"tree_label":"Imported tree 1","ntax":"23","rootedtree":"TRUE","title":"Tr125927","tree_kind":"NA","tree_type":"NA","tree_quality":"NA","phylotree_id":"tree_125927.phy"},{"tree_label":"Imported tree 1","ntax":"20","rootedtree":"TRUE","title":"Tr125928","tree_kind":"NA","tree_type":"NA","tree_quality":"NA","phylotree_id":"tree_125928.phy"},{"tree_label":"Imported tree 1","ntax":"18","rootedtree":"TRUE","title":"Tr125929","tree_kind":"NA","tree_type":"NA","tree_quality":"NA","phylotree_id":"tree_125929.phy"}]}