{"Authors":" NA","Year":" NA","Title":" NA","Journal":" NA","Volume":" NA","Issue":" NA","Pages":" NA","Keywords":" NA","DOI":" NA","Abstract":" NA","trees":[{"tree_label":"Fig.6","ntax":"69","rootedtree":"TRUE","title":"Tr134342","tree_kind":"Species Tree","tree_type":"Consensus","tree_quality":"Preferred Tree","phylotree_id":"tree_134342.phy"},{"tree_label":"Fig.3","ntax":"72","rootedtree":"TRUE","title":"Tr134328","tree_kind":"Species Tree","tree_type":"Consensus","tree_quality":"Preferred Tree","phylotree_id":"tree_134328.phy"},{"tree_label":"Fig.4","ntax":"63","rootedtree":"TRUE","title":"Tr134329","tree_kind":"Species Tree","tree_type":"Consensus","tree_quality":"Preferred Tree","phylotree_id":"tree_134329.phy"},{"tree_label":"Fig.5","ntax":"27","rootedtree":"TRUE","title":"Tr134327","tree_kind":"Species Tree","tree_type":"Consensus","tree_quality":"Preferred Tree","phylotree_id":"tree_134327.phy"}]}