{"Authors":" Fang Wu, Xiang Hua Wang, Zuo Hong Chen","Year":" 2022","Title":" Five new species and one new record of Lactarius\n(Russulaceae, Russulales) from central-southern China","Journal":"","Volume":"","Issue":"","Pages":"","Keywords":" ectomycorrhizal fungi, fagaceous forests, subtropical,\ntaxonomy, tropical","DOI":"","Abstract":"","trees":[{"tree_label":"Imported tree 1","ntax":"1","rootedtree":"TRUE","title":"Tr134762","tree_kind":"NA","tree_type":"NA","tree_quality":"NA","phylotree_id":"tree_134762.phy"},{"tree_label":"Imported tree 1","ntax":"78","rootedtree":"TRUE","title":"Tr134763","tree_kind":"NA","tree_type":"NA","tree_quality":"NA","phylotree_id":"tree_134763.phy"}]}